[{"Year":"3-1993","Andhra Pradesh":0,"Karnataka":0,"Kerala":0,"Tamil Nadu":0},{"Year":"3-1994","Andhra Pradesh":0,"Karnataka":0,"Kerala":0,"Tamil Nadu":0},{"Year":"3-1995","Andhra Pradesh":0,"Karnataka":0,"Kerala":0,"Tamil Nadu":0},{"Year":"3-1996","Andhra Pradesh":0,"Karnataka":0,"Kerala":0,"Tamil Nadu":0},{"Year":"3-1997","Andhra Pradesh":0,"Karnataka":0,"Kerala":0,"Tamil Nadu":0},{"Year":"3-1998","Andhra Pradesh":0,"Karnataka":0,"Kerala":0,"Tamil Nadu":0},{"Year":"3-1999","Andhra Pradesh":0,"Karnataka":0,"Kerala":0,"Tamil Nadu":0},{"Year":"3-2000","Andhra Pradesh":0,"Karnataka":0,"Kerala":0,"Tamil Nadu":0},{"Year":"3-2001","Andhra Pradesh":0,"Karnataka":0,"Kerala":0,"Tamil Nadu":0},{"Year":"3-2002","Andhra Pradesh":0,"Karnataka":0,"Kerala":0,"Tamil Nadu":0},{"Year":"3-2003","Andhra Pradesh":0,"Karnataka":0,"Kerala":0,"Tamil Nadu":0},{"Year":"3-2004","Andhra Pradesh":0,"Karnataka":0,"Kerala":0,"Tamil Nadu":0},{"Year":"3-2005","Andhra Pradesh":24.3535,"Karnataka":24.3535,"Kerala":24.3535,"Tamil Nadu":24.3535},{"Year":"3-2006","Andhra Pradesh":27.9779,"Karnataka":27.9779,"Kerala":27.9779,"Tamil Nadu":27.9779},{"Year":"3-2007","Andhra Pradesh":24.2894,"Karnataka":24.2894,"Kerala":24.2894,"Tamil Nadu":24.2894},{"Year":"3-2008","Andhra Pradesh":29.7553,"Karnataka":29.7553,"Kerala":29.7553,"Tamil Nadu":29.7553},{"Year":"3-2009","Andhra Pradesh":27.718952,"Karnataka":27.718952,"Kerala":27.718952,"Tamil Nadu":27.718952},{"Year":"3-2010","Andhra Pradesh":24.881624,"Karnataka":24.881624,"Kerala":24.881624,"Tamil Nadu":24.881624},{"Year":"3-2011","Andhra Pradesh":32.478956,"Karnataka":32.478956,"Kerala":32.478956,"Tamil Nadu":32.478956},{"Year":"3-2012","Andhra Pradesh":29.7986417,"Karnataka":29.7986417,"Kerala":29.7986417,"Tamil Nadu":29.7986417},{"Year":"3-2013","Andhra Pradesh":30.943,"Karnataka":30.943,"Kerala":30.943,"Tamil Nadu":30.943},{"Year":"3-2014","Andhra Pradesh":32.4143,"Karnataka":32.4143,"Kerala":32.4143,"Tamil Nadu":32.4143}]